LICENSE
README.md
setup.py
pixivcat/AppApi.py
pixivcat/__init__.py
pixivcat/base.py
pixivcat/bookmark.py
pixivcat/client.py
pixivcat/comments.py
pixivcat/exceptions.py
pixivcat/illust.py
pixivcat/novel.py
pixivcat/previews.py
pixivcat/session.py
pixivcat/tag.py
pixivcat/user.py
pixivcat.egg-info/PKG-INFO
pixivcat.egg-info/SOURCES.txt
pixivcat.egg-info/dependency_links.txt
pixivcat.egg-info/requires.txt
pixivcat.egg-info/top_level.txt