Metadata-Version: 2.1
Name: pixivcat
Version: 0.0.2
Summary: an async pixiv toolbox
Home-page: https://github.com/ShiroDoMain/pixivcat
Author: ShiroDoMain
Author-email: b1808107177@gmail.com
License: MIT
Keywords: pixiv async pixivdownloader
Platform: UNKNOWN
Classifier: Programming Language :: Python :: 3.7
Classifier: Programming Language :: Python :: 3.8
Classifier: Programming Language :: Python :: 3.9
License-File: LICENSE
